quaccatoo/__init__.py
quaccatoo/utils.py
quaccatoo/analysis/__init__.py
quaccatoo/analysis/analysis.py
quaccatoo/analysis/fit_functions.py
quaccatoo/exp_data/__init__.py
quaccatoo/exp_data/exp_data.py
quaccatoo/pulsed_sim/__init__.py
quaccatoo/pulsed_sim/predef_dd_seqs.py
quaccatoo/pulsed_sim/predef_seqs.py
quaccatoo/pulsed_sim/pulse_shapes.py
quaccatoo/pulsed_sim/pulsed_sim.py
quaccatoo/qsys/NV_sys.py
quaccatoo/qsys/P1_sys.py
quaccatoo/qsys/__init__.py
quaccatoo/qsys/qsys.py
quaccatoo-1.1.0.dist-info/METADATA
quaccatoo-1.1.0.dist-info/WHEEL
quaccatoo-1.1.0.dist-info/licenses/LICENSE
quaccatoo-1.1.0.dist-info/RECORD
