Metadata-Version: 2.4
Name: QuaCCAToo
Version: 1.1.0
Summary: Quantum Color Centers Analysis Toolbox
Project-URL: Homepage, https://github.com/QISS-HZB/QuaCCAToo
Project-URL: Source, https://github.com/QISS-HZB/QuaCCAToo
Project-URL: Documentation, https://qiss-hzb.github.io/QuaCCAToo/
Project-URL: Issues, https://github.com/QISS-HZB/QuaCCAToo/issues
Project-URL: PyPI, https://pypi.org/project/QuaCCAToo/
Project-URL: arXiv, https://arxiv.org/abs/2507.18759
Author-email: Lucas Tsunaki <lucastsunaki@hotmail.com>, Anmol Singh <anmol.singh@helmholtz-berlin.de>, Sergei Trofimov <sergei.trofimov@helmholtz-berlin.de>, Kseniia Volkova <kseniia.volkova@helmholtz-berlin.de>
Maintainer-email: Lucas Tsunaki <lucas.tsunaki@hotmail.com>, Anmol Singh <anmol.singh@helmholtz-berlin.de>
License-Expression: GPL-3.0-or-later
License-File: LICENSE
Classifier: Intended Audience :: Education
Classifier: Intended Audience :: Science/Research
Classifier: Natural Language :: English
Classifier: Programming Language :: Python :: 3
Classifier: Topic :: Scientific/Engineering :: Physics
Classifier: Topic :: Scientific/Engineering :: Quantum Computing
Requires-Python: >=3.9
Requires-Dist: dill
Requires-Dist: lmfit
Requires-Dist: matplotlib
Requires-Dist: numpy
Requires-Dist: qutip
Requires-Dist: scipy
Provides-Extra: dev
Requires-Dist: hatch; extra == 'dev'
Requires-Dist: pytest; extra == 'dev'
Requires-Dist: ruff; extra == 'dev'
Requires-Dist: ty; extra == 'dev'
